aci_mcp/__init__.py
aci_mcp/__main__.py
aci_mcp/apps_server.py
aci_mcp/unified_server.py
aci_mcp/vibeops_server.py
aci_mcp/common/__init__.py
aci_mcp/common/runners.py
aci_mcp/common/validators.py
aci_mcp-1.0.0b13.dist-info/METADATA
aci_mcp-1.0.0b13.dist-info/WHEEL
aci_mcp-1.0.0b13.dist-info/entry_points.txt
aci_mcp-1.0.0b13.dist-info/licenses/LICENSE
aci_mcp-1.0.0b13.dist-info/RECORD
